huaweicloudsdkoctopus/__init__.py
huaweicloudsdkoctopus/v2/__init__.py
huaweicloudsdkoctopus/v2/octopus_async_client.py
huaweicloudsdkoctopus/v2/octopus_client.py
huaweicloudsdkoctopus/v2/model/__init__.py
huaweicloudsdkoctopus/v2/model/alg_image_create_srlz.py
huaweicloudsdkoctopus/v2/model/alg_image_list_srlz.py
huaweicloudsdkoctopus/v2/model/algorithm_create_srlz.py
huaweicloudsdkoctopus/v2/model/algorithm_list_srlz.py
huaweicloudsdkoctopus/v2/model/batch_config_abc_info_srlz.py
huaweicloudsdkoctopus/v2/model/batch_config_evaluation_info_srlz.py
huaweicloudsdkoctopus/v2/model/batch_config_image_info_srlz.py
huaweicloudsdkoctopus/v2/model/batch_config_msg_notify_srlz.py
huaweicloudsdkoctopus/v2/model/batch_config_scenario_srlz.py
huaweicloudsdkoctopus/v2/model/batch_config_srlz.py
huaweicloudsdkoctopus/v2/model/batch_create_request.py
huaweicloudsdkoctopus/v2/model/batch_srlz.py
huaweicloudsdkoctopus/v2/model/build_create_srlz.py
huaweicloudsdkoctopus/v2/model/build_update_srlz.py
huaweicloudsdkoctopus/v2/model/category_f62_enum.py
huaweicloudsdkoctopus/v2/model/compilation_create_srlz.py
huaweicloudsdkoctopus/v2/model/compilation_update_srlz.py
huaweicloudsdkoctopus/v2/model/create_sim_algorithm_images_request.py
huaweicloudsdkoctopus/v2/model/create_sim_algorithm_images_response.py
huaweicloudsdkoctopus/v2/model/create_sim_algorithms_request.py
huaweicloudsdkoctopus/v2/model/create_sim_algorithms_response.py
huaweicloudsdkoctopus/v2/model/create_sim_batch_configs_request.py
huaweicloudsdkoctopus/v2/model/create_sim_batch_configs_response.py
huaweicloudsdkoctopus/v2/model/create_sim_batches_request.py
huaweicloudsdkoctopus/v2/model/create_sim_batches_response.py
huaweicloudsdkoctopus/v2/model/create_sim_extensions_request.py
huaweicloudsdkoctopus/v2/model/create_sim_extensions_response.py
huaweicloudsdkoctopus/v2/model/create_sim_sm_maps_request.py
huaweicloudsdkoctopus/v2/model/create_sim_sm_maps_response.py
huaweicloudsdkoctopus-3.1.184.dist-info/METADATA
huaweicloudsdkoctopus-3.1.184.dist-info/WHEEL
huaweicloudsdkoctopus-3.1.184.dist-info/licenses/LICENSE
huaweicloudsdkoctopus-3.1.184.dist-info/RECORD
